{
  "turnosDeVida": 5,
  "pRep": 50,
  "pMuerte": 50,
  "pClon": 50,
  "lado": 5,
  "altura": 5,
  "tiempoDeAparicion": 3,
  "probabilidadDeAparicion": 70,
  "vidaAguaSuma": 2,
  "pAgua": 16,
  "vidaComidaSuma": 1,
  "pComida": 16,
  "vidaMontanaResta": 1,
  "pMontana": 16,
  "pReproTesoroSuma": 20,
  "pTesoro": 16,
  "pClonacionBiblioteca": 10,
  "pBiblioteca": 16,
  "muertePozo": 0,
  "pPozo": 16,
  "celdas": {
    "primero": {
      "data": {
        "individuos": {},
        "recursos": {},
        "identificadorCelda": 0,
        "coordX": 0,
        "coordY": 0
      },
      "siguiente": {
        "data": {
          "individuos": {},
          "recursos": {},
          "identificadorCelda": 1,
          "coordX": 0,
          "coordY": 1
        },
        "siguiente": {
          "data": {
            "individuos": {},
            "recursos": {
              "primero": {
                "data": {
                  "tipo": 4,
                  "turnosDeVida": 2,
                  "posicion": 2,
                  "probabilidadGeneral": 70,
                  "probabilidadRecurso": 16,
                  "propiedad": 1
                }
              }
            },
            "identificadorCelda": 2,
            "coordX": 0,
            "coordY": 2
          },
          "siguiente": {
            "data": {
              "individuos": {},
              "recursos": {},
              "identificadorCelda": 3,
              "coordX": 0,
              "coordY": 3
            },
            "siguiente": {
              "data": {
                "individuos": {},
                "recursos": {
                  "primero": {
                    "data": {
                      "tipo": 0,
                      "turnosDeVida": 3,
                      "posicion": 4,
                      "probabilidadGeneral": 70,
                      "probabilidadRecurso": 16,
                      "propiedad": 1
                    },
                    "siguiente": {
                      "data": {
                        "tipo": 3,
                        "turnosDeVida": 3,
                        "posicion": 4,
                        "probabilidadGeneral": 70,
                        "probabilidadRecurso": 16,
                        "propiedad": 1
                      },
                      "siguiente": {
                        "data": {
                          "tipo": 4,
                          "turnosDeVida": 3,
                          "posicion": 4,
                          "probabilidadGeneral": 70,
                          "probabilidadRecurso": 16,
                          "propiedad": 1
                        }
                      }
                    }
                  }
                },
                "identificadorCelda": 4,
                "coordX": 0,
                "coordY": 4
              },
              "siguiente": {
                "data": {
                  "individuos": {},
                  "recursos": {
                    "primero": {
                      "data": {
                        "tipo": 2,
                        "turnosDeVida": 3,
                        "posicion": 5,
                        "probabilidadGeneral": 70,
                        "probabilidadRecurso": 16,
                        "propiedad": 1
                      },
                      "siguiente": {
                        "data": {
                          "tipo": 4,
                          "turnosDeVida": 3,
                          "posicion": 5,
                          "probabilidadGeneral": 70,
                          "probabilidadRecurso": 16,
                          "propiedad": 1
                        }
                      }
                    }
                  },
                  "identificadorCelda": 5,
                  "coordX": 1,
                  "coordY": 0
                },
                "siguiente": {
                  "data": {
                    "individuos": {},
                    "recursos": {
                      "primero": {
                        "data": {
                          "tipo": 0,
                          "turnosDeVida": 3,
                          "posicion": 6,
                          "probabilidadGeneral": 70,
                          "probabilidadRecurso": 16,
                          "propiedad": 1
                        },
                        "siguiente": {
                          "data": {
                            "tipo": 4,
                            "turnosDeVida": 3,
                            "posicion": 6,
                            "probabilidadGeneral": 70,
                            "probabilidadRecurso": 16,
                            "propiedad": 1
                          }
                        }
                      }
                    },
                    "identificadorCelda": 6,
                    "coordX": 1,
                    "coordY": 1
                  },
                  "siguiente": {
                    "data": {
                      "individuos": {},
                      "recursos": {},
                      "identificadorCelda": 7,
                      "coordX": 1,
                      "coordY": 2
                    },
                    "siguiente": {
                      "data": {
                        "individuos": {},
                        "recursos": {
                          "primero": {
                            "data": {
                              "tipo": 2,
                              "turnosDeVida": 2,
                              "posicion": 8,
                              "probabilidadGeneral": 70,
                              "probabilidadRecurso": 16,
                              "propiedad": 1
                            }
                          }
                        },
                        "identificadorCelda": 8,
                        "coordX": 1,
                        "coordY": 3
                      },
                      "siguiente": {
                        "data": {
                          "individuos": {},
                          "recursos": {
                            "primero": {
                              "data": {
                                "tipo": 1,
                                "turnosDeVida": 2,
                                "posicion": 9,
                                "probabilidadGeneral": 70,
                                "probabilidadRecurso": 16,
                                "propiedad": 1
                              },
                              "siguiente": {
                                "data": {
                                  "tipo": 3,
                                  "turnosDeVida": 2,
                                  "posicion": 9,
                                  "probabilidadGeneral": 70,
                                  "probabilidadRecurso": 16,
                                  "propiedad": 1
                                }
                              }
                            }
                          },
                          "identificadorCelda": 9,
                          "coordX": 1,
                          "coordY": 4
                        },
                        "siguiente": {
                          "data": {
                            "individuos": {},
                            "recursos": {
                              "primero": {
                                "data": {
                                  "tipo": 3,
                                  "turnosDeVida": 3,
                                  "posicion": 10,
                                  "probabilidadGeneral": 70,
                                  "probabilidadRecurso": 16,
                                  "propiedad": 1
                                }
                              }
                            },
                            "identificadorCelda": 10,
                            "coordX": 2,
                            "coordY": 0
                          },
                          "siguiente": {
                            "data": {
                              "individuos": {},
                              "recursos": {
                                "primero": {
                                  "data": {
                                    "tipo": 5,
                                    "turnosDeVida": 3,
                                    "posicion": 11,
                                    "probabilidadGeneral": 70,
                                    "probabilidadRecurso": 16,
                                    "propiedad": 1
                                  }
                                }
                              },
                              "identificadorCelda": 11,
                              "coordX": 2,
                              "coordY": 1
                            },
                            "siguiente": {
                              "data": {
                                "individuos": {},
                                "recursos": {
                                  "primero": {
                                    "data": {
                                      "tipo": 0,
                                      "turnosDeVida": 3,
                                      "posicion": 12,
                                      "probabilidadGeneral": 70,
                                      "probabilidadRecurso": 16,
                                      "propiedad": 1
                                    },
                                    "siguiente": {
                                      "data": {
                                        "tipo": 2,
                                        "turnosDeVida": 3,
                                        "posicion": 12,
                                        "probabilidadGeneral": 70,
                                        "probabilidadRecurso": 16,
                                        "propiedad": 1
                                      },
                                      "siguiente": {
                                        "data": {
                                          "tipo": 3,
                                          "turnosDeVida": 3,
                                          "posicion": 12,
                                          "probabilidadGeneral": 70,
                                          "probabilidadRecurso": 16,
                                          "propiedad": 1
                                        }
                                      }
                                    }
                                  }
                                },
                                "identificadorCelda": 12,
                                "coordX": 2,
                                "coordY": 2
                              },
                              "siguiente": {
                                "data": {
                                  "individuos": {},
                                  "recursos": {
                                    "primero": {
                                      "data": {
                                        "tipo": 0,
                                        "turnosDeVida": 3,
                                        "posicion": 13,
                                        "probabilidadGeneral": 70,
                                        "probabilidadRecurso": 16,
                                        "propiedad": 1
                                      },
                                      "siguiente": {
                                        "data": {
                                          "tipo": 3,
                                          "turnosDeVida": 3,
                                          "posicion": 13,
                                          "probabilidadGeneral": 70,
                                          "probabilidadRecurso": 16,
                                          "propiedad": 1
                                        }
                                      }
                                    }
                                  },
                                  "identificadorCelda": 13,
                                  "coordX": 2,
                                  "coordY": 3
                                },
                                "siguiente": {
                                  "data": {
                                    "individuos": {},
                                    "recursos": {
                                      "primero": {
                                        "data": {
                                          "tipo": 3,
                                          "turnosDeVida": 3,
                                          "posicion": 14,
                                          "probabilidadGeneral": 70,
                                          "probabilidadRecurso": 16,
                                          "propiedad": 1
                                        }
                                      }
                                    },
                                    "identificadorCelda": 14,
                                    "coordX": 2,
                                    "coordY": 4
                                  },
                                  "siguiente": {
                                    "data": {
                                      "individuos": {},
                                      "recursos": {
                                        "primero": {
                                          "data": {
                                            "tipo": 0,
                                            "turnosDeVida": 2,
                                            "posicion": 15,
                                            "probabilidadGeneral": 70,
                                            "probabilidadRecurso": 16,
                                            "propiedad": 1
                                          }
                                        }
                                      },
                                      "identificadorCelda": 15,
                                      "coordX": 3,
                                      "coordY": 0
                                    },
                                    "siguiente": {
                                      "data": {
                                        "individuos": {},
                                        "recursos": {
                                          "primero": {
                                            "data": {
                                              "tipo": 2,
                                              "turnosDeVida": 2,
                                              "posicion": 16,
                                              "probabilidadGeneral": 70,
                                              "probabilidadRecurso": 16,
                                              "propiedad": 1
                                            },
                                            "siguiente": {
                                              "data": {
                                                "tipo": 4,
                                                "turnosDeVida": 2,
                                                "posicion": 16,
                                                "probabilidadGeneral": 70,
                                                "probabilidadRecurso": 16,
                                                "propiedad": 1
                                              }
                                            }
                                          }
                                        },
                                        "identificadorCelda": 16,
                                        "coordX": 3,
                                        "coordY": 1
                                      },
                                      "siguiente": {
                                        "data": {
                                          "individuos": {
                                            "primero": {
                                              "data": {
                                                "tipo": 0,
                                                "id": 0,
                                                "turnosDeVida": 4,
                                                "generacion": 0,
                                                "padres": {},
                                                "pReproCadaIndividuo": 40,
                                                "pClonacionCadaIndividuo": 40,
                                                "celdaObjetivoNormal": 0,
                                                "colaIndividuo": {
                                                  "primero": {
                                                    "data": 4,
                                                    "siguiente": {
                                                      "data": 4
                                                    }
                                                  },
                                                  "ultimo": {
                                                    "data": 4
                                                  }
                                                }
                                              }
                                            }
                                          },
                                          "recursos": {
                                            "primero": {
                                              "data": {
                                                "tipo": 4,
                                                "turnosDeVida": 3,
                                                "posicion": 17,
                                                "probabilidadGeneral": 70,
                                                "probabilidadRecurso": 16,
                                                "propiedad": 1
                                              }
                                            }
                                          },
                                          "identificadorCelda": 17,
                                          "coordX": 3,
                                          "coordY": 2
                                        },
                                        "siguiente": {
                                          "data": {
                                            "individuos": {},
                                            "recursos": {
                                              "primero": {
                                                "data": {
                                                  "tipo": 1,
                                                  "turnosDeVida": 2,
                                                  "posicion": 18,
                                                  "probabilidadGeneral": 70,
                                                  "probabilidadRecurso": 16,
                                                  "propiedad": 1
                                                },
                                                "siguiente": {
                                                  "data": {
                                                    "tipo": 2,
                                                    "turnosDeVida": 3,
                                                    "posicion": 18,
                                                    "probabilidadGeneral": 70,
                                                    "probabilidadRecurso": 16,
                                                    "propiedad": 1
                                                  }
                                                }
                                              }
                                            },
                                            "identificadorCelda": 18,
                                            "coordX": 3,
                                            "coordY": 3
                                          },
                                          "siguiente": {
                                            "data": {
                                              "individuos": {},
                                              "recursos": {
                                                "primero": {
                                                  "data": {
                                                    "tipo": 4,
                                                    "turnosDeVida": 3,
                                                    "posicion": 19,
                                                    "probabilidadGeneral": 70,
                                                    "probabilidadRecurso": 16,
                                                    "propiedad": 1
                                                  }
                                                }
                                              },
                                              "identificadorCelda": 19,
                                              "coordX": 3,
                                              "coordY": 4
                                            },
                                            "siguiente": {
                                              "data": {
                                                "individuos": {},
                                                "recursos": {
                                                  "primero": {
                                                    "data": {
                                                      "tipo": 2,
                                                      "turnosDeVida": 2,
                                                      "posicion": 20,
                                                      "probabilidadGeneral": 70,
                                                      "probabilidadRecurso": 16,
                                                      "propiedad": 1
                                                    }
                                                  }
                                                },
                                                "identificadorCelda": 20,
                                                "coordX": 4,
                                                "coordY": 0
                                              },
                                              "siguiente": {
                                                "data": {
                                                  "individuos": {},
                                                  "recursos": {},
                                                  "identificadorCelda": 21,
                                                  "coordX": 4,
                                                  "coordY": 1
                                                },
                                                "siguiente": {
                                                  "data": {
                                                    "individuos": {},
                                                    "recursos": {
                                                      "primero": {
                                                        "data": {
                                                          "tipo": 0,
                                                          "turnosDeVida": 2,
                                                          "posicion": 22,
                                                          "probabilidadGeneral": 70,
                                                          "probabilidadRecurso": 16,
                                                          "propiedad": 1
                                                        },
                                                        "siguiente": {
                                                          "data": {
                                                            "tipo": 4,
                                                            "turnosDeVida": 2,
                                                            "posicion": 22,
                                                            "probabilidadGeneral": 70,
                                                            "probabilidadRecurso": 16,
                                                            "propiedad": 1
                                                          }
                                                        }
                                                      }
                                                    },
                                                    "identificadorCelda": 22,
                                                    "coordX": 4,
                                                    "coordY": 2
                                                  },
                                                  "siguiente": {
                                                    "data": {
                                                      "individuos": {},
                                                      "recursos": {
                                                        "primero": {
                                                          "data": {
                                                            "tipo": 5,
                                                            "turnosDeVida": 2,
                                                            "posicion": 23,
                                                            "probabilidadGeneral": 70,
                                                            "probabilidadRecurso": 16,
                                                            "propiedad": 1
                                                          },
                                                          "siguiente": {
                                                            "data": {
                                                              "tipo": 1,
                                                              "turnosDeVida": 3,
                                                              "posicion": 23,
                                                              "probabilidadGeneral": 70,
                                                              "probabilidadRecurso": 16,
                                                              "propiedad": 1
                                                            },
                                                            "siguiente": {
                                                              "data": {
                                                                "tipo": 3,
                                                                "turnosDeVida": 3,
                                                                "posicion": 23,
                                                                "probabilidadGeneral": 70,
                                                                "probabilidadRecurso": 16,
                                                                "propiedad": 1
                                                              }
                                                            }
                                                          }
                                                        }
                                                      },
                                                      "identificadorCelda": 23,
                                                      "coordX": 4,
                                                      "coordY": 3
                                                    },
                                                    "siguiente": {
                                                      "data": {
                                                        "individuos": {},
                                                        "recursos": {
                                                          "primero": {
                                                            "data": {
                                                              "tipo": 5,
                                                              "turnosDeVida": 2,
                                                              "posicion": 24,
                                                              "probabilidadGeneral": 70,
                                                              "probabilidadRecurso": 16,
                                                              "propiedad": 1
                                                            }
                                                          }
                                                        },
                                                        "identificadorCelda": 24,
                                                        "coordX": 4,
                                                        "coordY": 4
                                                      }
                                                    }
                                                  }
                                                }
                                              }
                                            }
                                          }
                                        }
                                      }
                                    }
                                  }
                                }
                              }
                            }
                          }
                        }
                      }
                    }
                  }
                }
              }
            }
          }
        }
      }
    }
  },
  "numIndividuosVivos": 1,
  "turnosJuego": 1
}